COPYING
MANIFEST
MANIFEST.in
README
README~
ez_setup.py
setup.py
setup_cxfreeze.py
Model_Builder.egg-info/PKG-INFO
Model_Builder.egg-info/SOURCES.txt
Model_Builder.egg-info/dependency_links.txt
Model_Builder.egg-info/entry_points.txt
Model_Builder.egg-info/requires.txt
Model_Builder.egg-info/top_level.txt
model_builder/Introduction.html
model_builder/MB.ico
model_builder/MBicon.py
model_builder/Model.py
model_builder/ModelBuilder_About.html
model_builder/PlotFigure.py
model_builder/PyMB.py
model_builder/The_main_Interface.html
model_builder/__init__.py
model_builder/__version__.py
model_builder/about.py
model_builder/backup_section.png
model_builder/cwt.png
model_builder/cwt.py
model_builder/filesave.png
model_builder/folder_open.png
model_builder/gnuplot.png
model_builder/graphics_section.png
model_builder/icones.py
model_builder/index.html
model_builder/lhs.py
model_builder/lhsframe.py
model_builder/lhsframe_glade.py
model_builder/mathematics_section.png
model_builder/odexml.py
model_builder/quivVarFrame.py
model_builder/quiver.png
model_builder/spreadsheet_section.png
model_builder/timemanagement_section.png
model_builder/uncertaintyMiniFrame.py
model_builder/wxFrame1.py
model_builder/wxFrame2.py
model_builder/wxMiniFrame1.py
model_builder/Examples/2eqs.ode
model_builder/Examples/3eqs.ode
model_builder/Examples/HH.ode
model_builder/Examples/bmeld_example.ode
model_builder/Examples/exponencial.ode
model_builder/Examples/gastric.ode
model_builder/Examples/lk.ode
model_builder/Examples/lotka-volterra.ode
model_builder/Examples/lotka-volterra_unc.spec
model_builder/Examples/nagumo.ode
model_builder/Examples/pk.ode
model_builder/Examples/pk_unc.spec
model_builder/Examples/sir.ode
model_builder/Examples/sirdemog.ode
model_builder/Examples/sprucebudworm.ode
model_builder/Examples/verhulst.ode