Metadata-Version: 1.0
Name: Model-Builder
Version: 0.4.8
Summary: Model Builder is a graphical ODE simulator
Home-page: http://model-builder.sourceforge.net
Author: Flavio Codeco Coelho
Author-email: fccoelho@gmail.com
License: UNKNOWN
Download-URL: http://sourceforge.net/project/showfiles.php?group_id=164374
Platform: UNKNOWN
